<?xml version="1.0" encoding="UTF-8"?>
<dataset>
    <!--Program workflow-->
    <!--TB Program-->
    <program_workflow  program_workflow_id="1"  program_id="2"  concept_id="159792"  creator="1"  date_created="2020-07-29 20:04:43"  retired="0"  changed_by="1"  date_changed="2020-07-29 20:06:21"  uuid="b70f609e-c3e8-4e4f-bd9e-97df5e95796a"/>
    <program_workflow  program_workflow_id="2"  program_id="2"  concept_id="166053"  creator="1"  date_created="2020-09-18 15:44:42"  retired="0"  changed_by="1"  date_changed="2020-09-18 16:09:17"  uuid="d6e3ed60-ffc7-4108-ab07-706d7b542d99"/>

    <!-- HIV Program - Regimen Status -->
    <program_workflow  program_workflow_id="3"  program_id="1"  concept_id="166214"  creator="1"  date_created="2021-02-05 12:56:14"  retired="0"  changed_by="1"  date_changed="2021-02-05 12:56:14"  uuid="4c30d724-dbcc-42db-ba9b-a9b9d2aadc00"/>


    <!-- Drug pick up model workflow-->
    <program_workflow  program_workflow_id="4"  program_id="1"  concept_id="166495"  creator="1"  date_created="2021-08-25 19:29:37"  retired="0"  changed_by="1"  date_changed="2021-08-25 19:33:56"  uuid="306c02b7-198e-4066-8b2c-39e40a1bcc53"/>

    <!-- DSDM patient workflow -->
    <program_workflow  program_workflow_id="5"  program_id="1"  concept_id="165143"  creator="1"  date_created="2024-03-17 15:13:17"  retired="0"  changed_by="1"  date_changed="2024-03-17 15:15:45"  uuid="b8d44412-9d8a-422f-8952-7fe15997f8b6"/>


    <!--Program Workflow State-->
    <!--TB Treatment Phase -->
    <program_workflow_state  program_workflow_state_id="1"  program_workflow_id="1"  concept_id="159795"  initial="1"  terminal="0"  creator="1"  date_created="2020-07-29 20:06:21"  retired="0"  uuid="0e2ff228-8dab-491d-9457-aaa47764ef8a"/>
    <program_workflow_state  program_workflow_state_id="2"  program_workflow_id="1"  concept_id="159794"  initial="1"  terminal="0"  creator="1"  date_created="2020-07-29 20:06:21"  retired="0"  uuid="2fafcc3a-b5e2-4fb2-b534-d9b5f3e91b26"/>
    <program_workflow_state  program_workflow_state_id="3"  program_workflow_id="1"  concept_id="159793"  initial="1"  terminal="0"  creator="1"  date_created="2020-07-29 21:17:16"  retired="0"  uuid="031d22b8-4fde-45ba-9e0a-6b87337b29f3"/>

    <!--TB Infection Type/Level -->
    <program_workflow_state  program_workflow_state_id="4"  program_workflow_id="2"  concept_id="166119"  initial="1"  terminal="0"  creator="1"  date_created="2020-09-18 15:47:17"  retired="0" uuid="dc3fbc52-15a9-444c-99d1-65f01f9199dd"/>
    <program_workflow_state  program_workflow_state_id="5"  program_workflow_id="2"  concept_id="156080"  initial="1"  terminal="0"  creator="1"  date_created="2020-09-18 15:47:17"  retired="0" uuid="673966b1-e181-4b46-a526-f7ac6954c59b"/>

    <!--Program Attributes-->
    <!--TB Program Attribute -->
    <program_attribute_type  program_attribute_type_id="3"  name="TB District No."  description="The number that Identifies a patient in a TB program at District level"   datatype="org.openmrs.customdatatype.datatype.FreeTextDatatype"  min_occurs="0"    creator="1"  date_created="2020-07-29 09:30:34"     uuid="af9bac5e-d245-11ea-87d0-0242ac130003"/>
    <program_attribute_type  program_attribute_type_id="4"  name="TB Health Unit TB No."  description="The number that Identifies a patient in a TB Program at Health Center Level"   datatype="org.openmrs.customdatatype.datatype.FreeTextDatatype"  min_occurs="0"    creator="1"  date_created="2020-07-29 09:30:34"     uuid="af9baf06-d245-11ea-87d0-0242ac130003"/>
    <program_attribute_type  program_attribute_type_id="5"  name="TB Regimen"  description="The overall regimen the patient in a TB program is currently on"   datatype="org.openmrs.customdatatype.datatype.FreeTextDatatype"  min_occurs="0"    creator="1"  date_created="2020-07-29 09:29:51"     uuid="af9bb0c8-d245-11ea-87d0-0242ac130003"/>
    <program_attribute_type  program_attribute_type_id="6"  name="Initial Phase Regimen"  description="The regimen the patient is currently on when in Initial Phase"   datatype="org.openmrs.customdatatype.datatype.FreeTextDatatype"  min_occurs="0"    creator="1"  date_created="2020-07-29 09:30:34"     uuid=" af9bb1a4-d245-11ea-87d0-0242ac130003"/>
    <program_attribute_type  program_attribute_type_id="7"  name="Continuation Phase Regimen"  description="The regimen the patient is currently on when in Continuation Phase"   datatype="org.openmrs.customdatatype.datatype.FreeTextDatatype"  min_occurs="0"    creator="1"  date_created="2020-07-29 09:30:34"     uuid="af9bb26c-d245-11ea-87d0-0242ac130003"/>
    <program_attribute_type  program_attribute_type_id="8"  name="DR TB No"  description="The number that Identifies a patient in a TB program Who is Drug resistant"   datatype="org.openmrs.customdatatype.datatype.FreeTextDatatype"  min_occurs="0"    creator="1"  date_created="2020-07-29 09:30:34"     uuid="1628fa4e-fda2-11ea-adc1-0242ac120002"/>

    <!-- HIV Program - ART Regimen Lines -->
    <program_workflow_state  program_workflow_state_id="11"  program_workflow_id="3"  concept_id="90271"  initial="1"  terminal="0"  creator="1"  date_created="2020-07-29 20:06:21"  retired="0"  uuid="ab6d1f1d-fcf6-4255-8b6f-2bf8959ad8f2"/>
    <program_workflow_state  program_workflow_state_id="12"  program_workflow_id="3"  concept_id="90305"  initial="1"  terminal="0"  creator="1"  date_created="2020-07-29 20:06:21"  retired="0"  uuid="9a42a3ad-d8a4-4f2e-9fa0-04d5f2e6436e"/>
    <program_workflow_state  program_workflow_state_id="13"  program_workflow_id="3"  concept_id="162987"  initial="1"  terminal="0"  creator="1"  date_created="2020-07-29 21:17:16"  retired="0"  uuid="5d2d0e7e-69a6-408a-b5ce-8d93fb72bc21"/>

    <!-- HIV Program - DSDM workflow -->
    <program_workflow_state  program_workflow_state_id="17"  program_workflow_id="5"  concept_id="165138"  initial="1"  terminal="0"  creator="1"  date_created="2024-03-17 15:15:44"  retired="0"  uuid="4eae684a-ee1f-4f62-87f3-e3e58c91f417"/>
    <program_workflow_state  program_workflow_state_id="18"  program_workflow_id="5"  concept_id="165140"  initial="1"  terminal="0"  creator="1"  date_created="2024-03-17 15:15:44"  retired="0"  uuid="6b4906b1-388c-4984-974a-81e6f86f7737"/>
    <program_workflow_state  program_workflow_state_id="19"  program_workflow_id="5"  concept_id="165139"  initial="1"  terminal="0"  creator="1"  date_created="2024-03-17 15:15:44"  retired="0"  uuid="5e122a20-3e23-4e65-bb1b-9f1324f97396"/>
    <program_workflow_state  program_workflow_state_id="20"  program_workflow_id="5"  concept_id="165141"  initial="1"  terminal="0"  creator="1"  date_created="2024-03-17 15:15:44"  retired="0"  uuid="0ca3db87-567f-4159-acc0-0ec14d0b8036"/>
    <program_workflow_state  program_workflow_state_id="21"  program_workflow_id="5"  concept_id="165142"  initial="1"  terminal="0"  creator="1"  date_created="2024-03-17 15:15:44"  retired="0"  uuid="7e2acb9c-25e9-4b8f-b012-8436051d5c32"/>
    <!-- HIV Program - Attributes -->
    <program_attribute_type  program_attribute_type_id="9"   name="ART Baseline Regimen"  description="The regimen the patient started with on the start of ART"  datatype="org.openmrs.customdatatype.datatype.ConceptDatatype" min_occurs="0" max_occurs="1" creator="1" date_created="2020-07-29 09:30:34" uuid="f19f1d6e-5d44-4523-9352-4988144021e6"/>
    <program_attribute_type  program_attribute_type_id="10"  name="ART Baseline Regimen Start Date"  description="The date the patient started ART"   datatype="org.openmrs.customdatatype.datatype.DateDatatype"  min_occurs="0" max_occurs="1"  creator="1"  date_created="2020-07-29 09:30:34"     uuid="6bcdd5ea-c140-4edf-9f57-77b0584a196d"/>
    <program_attribute_type  program_attribute_type_id="11"  name="Current Regimen"  description="Patient Current Regimen" datatype="org.openmrs.customdatatype.datatype.ConceptDatatype"  min_occurs="0" max_occurs="1" creator="1"  date_created="2020-07-29 09:29:51"  uuid="3d6b3fbc-e5dd-4909-9e68-8bedf41e8437"/>
    <program_attribute_type  program_attribute_type_id="12"  name="Current Regimen Start Date"  description="Current Regimen Start Date" datatype="org.openmrs.customdatatype.datatype.DateDatatype"  min_occurs="0" max_occurs="1"  creator="1"  date_created="2020-07-29 09:30:34"  uuid="9b9b5967-4ac2-420b-9024-e8cea90514c2"/>
    <program_attribute_type  program_attribute_type_id="13"  name="HIV Verification Date"  description="The date of verification of the HIV infection at this facility"   datatype="org.openmrs.customdatatype.datatype.DateDatatype"  min_occurs="0" max_occurs="1"    creator="1"  date_created="2020-07-29 09:30:34"  uuid="dd75e7b0-62d4-4c90-821d-66846e05fb7e"/>
    <program_attribute_type  program_attribute_type_id="14"  name="Date Enrolled into HIV Care"  description="The date the patient was enrolled into HIV Care" datatype="org.openmrs.customdatatype.datatype.DateDatatype" min_occurs="0" max_occurs="1" creator="1" date_created="2020-07-29 09:30:34" uuid="8c4350b4-5c39-4dff-bc73-c5089a527ebc"/>
    <program_attribute_type  program_attribute_type_id="15"   name="Other ART Baseline Regimen"  description="The non coded regimen the patient started with on the start of ART"  datatype="org.openmrs.customdatatype.datatype.ConceptDatatype" min_occurs="0" max_occurs="1" creator="1" date_created="2020-07-29 09:30:34" uuid="479d226d-a1c9-4af2-8c08-f2d740817f08"/>

    <!-- CDDP Category -->
    <program_workflow_state  program_workflow_state_id="14"  program_workflow_id="4"  concept_id="166496"  initial="1"  terminal="0"  creator="1"  date_created="2021-08-25 19:33:45"  retired="0"  changed_by="1"  date_changed="2021-08-25 19:33:56"  uuid="d77cc565-5e53-4633-8fc7-956cfc1831d9"/>
    <program_workflow_state  program_workflow_state_id="15"  program_workflow_id="4"  concept_id="166498"  initial="1"  terminal="0"  creator="1"  date_created="2021-08-25 19:33:45"  retired="0"  changed_by="1"  date_changed="2021-08-25 19:33:56"  uuid="a6a0ab45-b7dc-43b2-b28c-45a91f968ebf"/>
    <program_workflow_state  program_workflow_state_id="16"  program_workflow_id="4"  concept_id="166497"  initial="1"  terminal="0"  creator="1"  date_created="2021-08-25 19:33:45"  retired="0"  changed_by="1"  date_changed="2021-08-25 19:33:56"  uuid="1b9b83d4-eaca-40da-a7c6-53b8ea3436ad"/>

    <!-- Retire DSDM Programs -->
    <program  program_id="5"  concept_id="165138" creator="2"  date_created="2019-08-21 09:14:57"  changed_by="1"  date_changed="2024-03-17 15:55:01"  retired="1"  name="FBIM"  description="Facility Based Individual Management a DSDM model for patients that need extra management at the health centre"  uuid="de5d54ae-c304-11e8-9ad0-529269fb1459"/>
    <program  program_id="6"  concept_id="165140" creator="2"  date_created="2019-08-21 09:14:57"  changed_by="1"  date_changed="2019-08-21 09:14:57"  retired="1"  name="FGB"  description="Facility Based Groups a DSDM for stable or unstable clients who need peer support"  uuid="de5d5b34-c304-11e8-9ad0-529269fb1459"/>
    <program  program_id="7"  concept_id="165139" creator="2"  date_created="2019-08-21 09:14:57"  changed_by="1"  date_changed="2019-08-21 09:14:57"  retired="1"  name="FTR"  description="Fast Track Drug Refill is a DSDM Model for patients who only pick drugs at the health centre"  uuid="de5d5896-c304-11e8-9ad0-529269fb1459"/>
    <program  program_id="8"  concept_id="165141" creator="2"  date_created="2019-08-21 09:14:57"  changed_by="1"  date_changed="2024-03-17 15:53:50"  retired="1"  name="CCLAD"  description="Community Client Led ART Delivery is a DSDM  Model with client lead groups with rotation drug pickup by client them selves and distribution"  uuid="de5d5da0-c304-11e8-9ad0-529269fb1459"/>
    <program  program_id="9"  concept_id="165142" creator="2"  date_created="2019-08-21 09:14:57"  changed_by="1"  date_changed="2024-03-17 15:52:23"  retired="1"  name="CDDP"  description="Community Drug Distribution Point DSDM Model in community where patients pick drugs from a distribution point in community set by their health centre"  uuid="de5d6034-c304-11e8-9ad0-529269fb1459"/>
</dataset>